Metadata-Version: 2.1
Name: ltphotonics
Version: 1.0.0
Summary: Python Library for interfacing with Light Trace Photonics hardware.
Home-page: https://github.com/ltphotonics/ltphotonics
Author: Light Trace Photonics Ltd
Author-email: contact@ltphotonics.co.uk
Classifier: Programming Language :: Python :: 3
Classifier: Operating System :: OS Independent
License-File: LICENSE
